LICENSE
MANIFEST.in
README.rst
setup.py
django_russian_fields.egg-info/PKG-INFO
django_russian_fields.egg-info/SOURCES.txt
django_russian_fields.egg-info/dependency_links.txt
django_russian_fields.egg-info/top_level.txt
russian_fields/__init__.py
russian_fields/fields.py
russian_fields/validators.py
russian_fields/models/__init__.py
russian_fields/models/fields.py