Metadata-Version: 1.1
Name: django-russian-fields
Version: 0.1.3
Summary: A simple Django app that provides fields like INNField, OGRNField etc.
Home-page: https://github.com/eternalfame/django-russian_fields
Author: Vyacheslav Sukhenko
Author-email: eternalfame@mail.ru
License: MIT License
Platform: UNKNOWN
Classifier: Environment :: Web Environment
Classifier: Framework :: Django
Classifier: Intended Audience :: Developers
Classifier: License :: OSI Approved :: MIT License
Classifier: Operating System :: OS Independent
Classifier: Programming Language :: Python
Classifier: Topic :: Internet :: WWW/HTTP
Classifier: Topic :: Internet :: WWW/HTTP :: Dynamic Content
